{
  "author": "Alexandre Sirko",
  "email": "sirko.alexandre@gmail.com",
  "title": "Éléments d'architecture logiciel",
  "logos": ["~/logo_ynov.png"],
  "chapters": [
    {
      "title": "Liste des sujets",
      "pages": ["~/0.summary/0.subjective.md", "~/0.summary/1.summary.md", "~/0.summary/2.principles.md"]
    },
    {
      "title": "Quelles architectures ?",
      "pages": ["~/1.archi/0.schema.md", "~/1.archi/1.archi.md"]
    },
    {
      "title": "Modélisation et structure de données",
      "pages": [
        "~/2.modelisation/0.why.md",
        "~/2.modelisation/1.uml.md",
        "~/2.modelisation/2.bpmn.md",
        "~/2.modelisation/3.data-structure.md"
      ]
    },
    {
      "title": "Stockage des données et NoSQL",
      "pages": ["~/3.db/0.relational.md", "~/3.db/1.nosql.md"]
    },
    {
      "title": "Modularisation",
      "pages": ["~/4.modularisation/0.how.md", "~/4.modularisation/1.di.md"]
    },
    {
      "title": "Quelques patterns récurrents",
      "pages": [
        "~/5.patterns/0.singleton.md",
        "~/5.patterns/1.immutability.md",
        "~/5.patterns/2.redux.md",
        "~/5.patterns/3.polymorphism.md"
      ]
    },
    {
      "title": "Mono-repo vs multi-repo",
      "pages": ["~/6.repo/0.multi.md", "~/6.repo/1.mono.md"]
    },
    {
      "title": "Bonus",
      "pages": [
        "~/7.bonus/0.restfull.md",
        "~/7.bonus/1.xml.md",
        "~/7.bonus/2.functional.md",
        "~/7.bonus/3.stateless.md"
      ]
    }
  ]
}
